open_api_maker_kamaalio/__init__.py
open_api_maker_kamaalio/cli.py
open_api_maker_kamaalio/enums.py
open_api_maker_kamaalio/main.py
open_api_maker_kamaalio/swagger_types.py
open_api_maker_kamaalio-0.0.2.dist-info/METADATA
open_api_maker_kamaalio-0.0.2.dist-info/WHEEL
open_api_maker_kamaalio-0.0.2.dist-info/entry_points.txt
open_api_maker_kamaalio-0.0.2.dist-info/top_level.txt
open_api_maker_kamaalio-0.0.2.dist-info/RECORD
